[{"nombrepelicula":"Cars","Genero":"Animaci\u00f3n","Duracion":"1h 57m","Clasificacion":"AA","Protagonistas":"Owen Wilson, Larry The Cable guy, Paul Newman."},{"nombrepelicula":"Shrek","Genero":"Animaci\u00f3n","Duracion":"1h 35m","Clasificacion":"AA","Protagonistas":"Mike Myers, Eddie Murphy, Cameron Diaz, John Lithgow."},{"nombrepelicula":"Once Upon a Time in Hollywood","Genero":"Comedia\/Drama","Duracion":"2h 40m","Clasificacion":"B15","Protagonistas":"Leonardo Dicaprio, Brad Pitt, Al Pacino, Margot Robbie."}]